garak/__init__.py
garak/__main__.py
garak/_config.py
garak/_plugins.py
garak/attempt.py
garak/cli.py
garak/command.py
garak/configurable.py
garak/exception.py
garak/interactive.py
garak/langservice.py
garak/payloads.py
garak/report.py
garak/analyze/__init__.py
garak/analyze/aggregate_reports.py
garak/analyze/analyze_log.py
garak/analyze/calibration.py
garak/analyze/count_tokens.py
garak/analyze/get_tree.py
garak/analyze/misp.py
garak/analyze/perf_stats.py
garak/analyze/qual_review.py
garak/analyze/report_avid.py
garak/analyze/report_digest.py
garak/analyze/templates/digest_about_z.jinja
garak/analyze/templates/digest_detector.jinja
garak/analyze/templates/digest_end_module.jinja
garak/analyze/templates/digest_footer.jinja
garak/analyze/templates/digest_group.jinja
garak/analyze/templates/digest_header.jinja
garak/analyze/templates/digest_probe.jinja
garak/buffs/__init__.py
garak/buffs/base.py
garak/buffs/encoding.py
garak/buffs/low_resource_languages.py
garak/buffs/lowercase.py
garak/buffs/paraphrase.py
garak/configs/bag.yaml
garak/configs/broad.yaml
garak/configs/default.yaml
garak/configs/fast.yaml
garak/configs/full.yaml
garak/configs/long_attack_gen.yaml
garak/configs/notox.yaml
garak/configs/tox_and_buffs.yaml
garak/data/__init__.py
garak/data/banners
garak/data/book_cloze.tsv
garak/data/book_cloze_80.tsv
garak/data/graph_connectivity.json
garak/data/guardian_cloze.tsv
garak/data/inthewild_jailbreak_llms.json
garak/data/ldnoobw-en.txt
garak/data/nyt_cloze.tsv
garak/data/ofcom-potentially-offensive.txt
garak/data/potter_cloze.tsv
garak/data/primality_testing.json
garak/data/profanity_en.csv
garak/data/safebench_filenames.txt
garak/data/safebenchtiny_filenames.txt
garak/data/senator_search.json
garak/data/slurprompts.jsonl
garak/data/slurprompts_mini.jsonl
garak/data/slursreclaimedslurs.txt
garak/data/tags.misp.tsv
garak/data/truefalse_falseclaims.txt
garak/data/truefalse_falseclaims_50.txt
garak/data/typology_payloads.tsv
garak/data/autodan/autodan_init.txt
garak-0.13.2.dist-info/entry_points.txt
garak-0.13.2.dist-info/licenses/LICENSE
garak-0.13.2.dist-info/WHEEL
garak-0.13.2.dist-info/METADATA
garak-0.13.2.dist-info/RECORD
