Metadata-Version: 2.4
Name: garak
Version: 0.13.2
Summary: LLM vulnerability scanner
Author: nv052193, Mads Kongsbak, Tianhao Li, Phyllis Poh, Razvan Dinu, Zander Mackie, Greg Stephens, Ahsan Ayub, Jonathan Liberman, Gustav Fredrikson, Oh Tien Cheng, Brain John, Naman Mishra, Soumili Nandi, Arjun Krishna, Mihailo Milenkovic, Kai Greshake, Martin Borup-Larsen, Emmanuel Ferdman, Eric Therond, Zoe Nolan, Harsh Raj, Shine-afk, Rafael Sandroni, Eric Hacker, Blessed Uyo, Ikko Eltociear Ashimine, iamnotcj, Dwight Temple, Shane Rosse, Masaya Ogushi, Viktor T. Zetterberg, Erwan Roussel, 
Author-email: Leon Derczynski <lderczynski@nvidia.com>, Subho Majumdar <subho@vijil.ai>, Erick Galinkin <egalinkin@nvidia.com>, Jeffrey Martin <jemartin@nvidia.com>
Requires-Python: >=3.10
License-Expression: Apache-2.0
Classifier: Development Status :: 3 - Alpha
Classifier: Programming Language :: Python :: 3.10
Classifier: Programming Language :: Python :: 3.11
Classifier: Programming Language :: Python :: 3.12
Classifier: Operating System :: OS Independent
License-File: LICENSE
Requires-Dist: base2048>=0.1.3
Requires-Dist: transformers>=4.51.3,<4.57.0
Requires-Dist: datasets>=3.0.0,<4.0
Requires-Dist: colorama>=0.4.3
Requires-Dist: tqdm>=4.67.1
Requires-Dist: cohere>=5.16.0
Requires-Dist: openai>=1.45.0,<2
Requires-Dist: replicate>=0.8.3
Requires-Dist: google-api-python-client>=2.0
Requires-Dist: backoff>=2.1.1
Requires-Dist: rapidfuzz>=3.0.0
Requires-Dist: jinja2>=3.1.6
Requires-Dist: nltk>=3.9.1
Requires-Dist: accelerate>=0.23.0
Requires-Dist: avidtools==0.1.2
Requires-Dist: stdlibs>=2022.10.9
Requires-Dist: langchain>=0.3.25,<1.0.0
Requires-Dist: nemollm>=0.3.0
Requires-Dist: cmd2==2.4.3
Requires-Dist: torch>=2.6.0
Requires-Dist: sentencepiece>=0.1.99
Requires-Dist: markdown>=3.4.3
Requires-Dist: numpy>=2.0.0
Requires-Dist: zalgolib>=0.2.2
Requires-Dist: ecoji>=0.1.1
Requires-Dist: deepl==1.17.0
Requires-Dist: fschat>=0.2.36
Requires-Dist: litellm>=1.68.1
Requires-Dist: jsonpath-ng>=1.6.1
Requires-Dist: huggingface_hub>=0.21.0
Requires-Dist: python-magic-bin>=0.4.14; sys_platform == "win32"
Requires-Dist: python-magic>=0.4.21; sys_platform != "win32"
Requires-Dist: lorem==0.1.1
Requires-Dist: xdg-base-dirs>=6.0.1
Requires-Dist: wn==0.9.5
Requires-Dist: ollama>=0.4.7
Requires-Dist: nvidia-riva-client==2.16.0
Requires-Dist: google-cloud-translate>=2.0.4
Requires-Dist: grpcio-tools>=1.71.0
Requires-Dist: langdetect==1.0.9
Requires-Dist: tiktoken>=0.7.0
Requires-Dist: mistralai==1.5.2
Requires-Dist: pillow>=10.4.0
Requires-Dist: ftfy>=6.3.1
Requires-Dist: soundfile>=0.13.1 ; extra == "audio"
Requires-Dist: librosa>=0.10.2 ; extra == "audio"
Requires-Dist: scipy>=1.14.0 ; extra == "calibration"
Requires-Dist: detoxify>=0.5.0 ; extra == "dra"
Requires-Dist: black==24.4.2 ; extra == "lint"
Requires-Dist: pylint>=3.1.0 ; extra == "lint"
Requires-Dist: pytest>=8.0 ; extra == "tests"
Requires-Dist: pytest-mock>=3.14.0 ; extra == "tests"
Requires-Dist: requests-mock==1.12.1 ; extra == "tests"
Requires-Dist: respx>=0.21.1 ; extra == "tests"
Requires-Dist: pytest-cov>=5.0.0 ; extra == "tests"
Requires-Dist: pytest_httpserver>=1.1.0 ; extra == "tests"
Requires-Dist: langcodes>=3.4.0 ; extra == "tests"
Project-URL: Bug Tracker, https://github.com/NVIDIA/garak/issues
Project-URL: Homepage, https://github.com/NVIDIA/garak
Provides-Extra: audio
Provides-Extra: calibration
Provides-Extra: dra
Provides-Extra: lint
Provides-Extra: tests
